KI_Inst_design_template/KIEL Wortbildmarke black.png
KI_Inst_design_template/KI_Inst_design_template.py
KI_Inst_design_template/__init__.py
ki_inst_design_template-0.0.5.dist-info/METADATA
ki_inst_design_template-0.0.5.dist-info/WHEEL
ki_inst_design_template-0.0.5.dist-info/licenses/LICENSE
ki_inst_design_template-0.0.5.dist-info/RECORD
