Metadata-Version: 2.1
Name: KI_Inst_design_template
Version: 0.0.5
Summary: Update of Secondary Colors
Project-URL: Homepage, https://github.com/kielinstitute/kielinstitutPython
Project-URL: Issues, https://github.com/kielinstitute/kielinstitutPython/issues
Author-email: Florian Ivan Hinrichsen <florian.hinrichsen@ifw-kiel.de>
License: All Rights Reserved
Classifier: Operating System :: OS Independent
Classifier: Programming Language :: Python :: 3
Requires-Python: >=3.10
